<?xml version="1.0" encoding="UTF-8"?>
<Mpeg7 xmlns="urn:mpeg:mpeg7:schema:2001" xmlns:xsi="http://www.w3.org/2001/XMLSchema-instance" xmlns:mpeg7="urn:mpeg:mpeg7:schema:2001" xsi:schemaLocation="urn:mpeg:mpeg7:schema:2001 Mpeg7-2001.xsd">
    <Description xsi:type="ContentEntityType">
        <MultimediaContent xsi:type="VideoType">
            <Video id="TRECVID2016_36031">
                <MediaLocator><MediaUri>Paramimechines._-o-_.pmec_512kb.mp4</MediaUri></MediaLocator>
                <MediaTime>
                    <MediaTimePoint>T00:00:00:0F25</MediaTimePoint>
                    <MediaDuration>PT6M46S22N25F</MediaDuration>
                </MediaTime>
                <TemporalDecomposition gap="false" overlap="false">
                    <VideoSegment id="shot36031_1">
                        <MediaTime>
                            <MediaTimePoint>T00:00:00:0F25</MediaTimePoint>
                            <MediaDuration>PT8S16N25F</MediaDuration>
                        </MediaTime>
                        <TemporalDecomposition>
                            <VideoSegment id="shot36031_1_RKF">
                                <MediaTime>
                                    <MediaTimePoint>T00:00:05:8F25</MediaTimePoint>
                                </MediaTime>
                            </VideoSegment>
                        </TemporalDecomposition>
                    </VideoSegment>
                    <VideoSegment id="shot36031_2">
                        <MediaTime>
                            <MediaTimePoint>T00:00:08:16F25</MediaTimePoint>
                            <MediaDuration>PT17N25F</MediaDuration>
                        </MediaTime>
                        <TemporalDecomposition>
                            <VideoSegment id="shot36031_2_RKF">
                                <MediaTime>
                                    <MediaTimePoint>T00:00:08:16F25</MediaTimePoint>
                                </MediaTime>
                            </VideoSegment>
                        </TemporalDecomposition>
                    </VideoSegment>
                    <VideoSegment id="shot36031_3">
                        <MediaTime>
                            <MediaTimePoint>T00:00:09:8F25</MediaTimePoint>
                            <MediaDuration>PT12S10N25F</MediaDuration>
                        </MediaTime>
                        <TemporalDecomposition>
                            <VideoSegment id="shot36031_3_RKF">
                                <MediaTime>
                                    <MediaTimePoint>T00:00:15:19F25</MediaTimePoint>
                                </MediaTime>
                            </VideoSegment>
                        </TemporalDecomposition>
                    </VideoSegment>
                    <VideoSegment id="shot36031_4">
                        <MediaTime>
                            <MediaTimePoint>T00:00:21:18F25</MediaTimePoint>
                            <MediaDuration>PT5S23N25F</MediaDuration>
                        </MediaTime>
                        <TemporalDecomposition>
                            <VideoSegment id="shot36031_4_RKF">
                                <MediaTime>
                                    <MediaTimePoint>T00:00:24:10F25</MediaTimePoint>
                                </MediaTime>
                            </VideoSegment>
                        </TemporalDecomposition>
                    </VideoSegment>
                    <VideoSegment id="shot36031_5">
                        <MediaTime>
                            <MediaTimePoint>T00:00:27:16F25</MediaTimePoint>
                            <MediaDuration>PT12S0N25F</MediaDuration>
                        </MediaTime>
                        <TemporalDecomposition>
                            <VideoSegment id="shot36031_5_RKF">
                                <MediaTime>
                                    <MediaTimePoint>T00:00:33:16F25</MediaTimePoint>
                                </MediaTime>
                            </VideoSegment>
                        </TemporalDecomposition>
                    </VideoSegment>
                    <VideoSegment id="shot36031_6">
                        <MediaTime>
                            <MediaTimePoint>T00:00:39:16F25</MediaTimePoint>
                            <MediaDuration>PT14S20N25F</MediaDuration>
                        </MediaTime>
                        <TemporalDecomposition>
                            <VideoSegment id="shot36031_6_RKF">
                                <MediaTime>
                                    <MediaTimePoint>T00:00:46:23F25</MediaTimePoint>
                                </MediaTime>
                            </VideoSegment>
                        </TemporalDecomposition>
                    </VideoSegment>
                    <VideoSegment id="shot36031_7">
                        <MediaTime>
                            <MediaTimePoint>T00:00:54:11F25</MediaTimePoint>
                            <MediaDuration>PT21S4N25F</MediaDuration>
                        </MediaTime>
                        <TemporalDecomposition>
                            <VideoSegment id="shot36031_7_RKF">
                                <MediaTime>
                                    <MediaTimePoint>T00:01:04:6F25</MediaTimePoint>
                                </MediaTime>
                            </VideoSegment>
                        </TemporalDecomposition>
                    </VideoSegment>
                    <VideoSegment id="shot36031_8">
                        <MediaTime>
                            <MediaTimePoint>T00:01:15:15F25</MediaTimePoint>
                            <MediaDuration>PT23N25F</MediaDuration>
                        </MediaTime>
                        <TemporalDecomposition>
                            <VideoSegment id="shot36031_8_RKF">
                                <MediaTime>
                                    <MediaTimePoint>T00:01:16:1F25</MediaTimePoint>
                                </MediaTime>
                            </VideoSegment>
                        </TemporalDecomposition>
                    </VideoSegment>
                    <VideoSegment id="shot36031_9">
                        <MediaTime>
                            <MediaTimePoint>T00:01:16:13F25</MediaTimePoint>
                            <MediaDuration>PT14N25F</MediaDuration>
                        </MediaTime>
                        <TemporalDecomposition>
                            <VideoSegment id="shot36031_9_RKF">
                                <MediaTime>
                                    <MediaTimePoint>T00:01:16:24F25</MediaTimePoint>
                                </MediaTime>
                            </VideoSegment>
                        </TemporalDecomposition>
                    </VideoSegment>
                    <VideoSegment id="shot36031_10">
                        <MediaTime>
                            <MediaTimePoint>T00:01:17:2F25</MediaTimePoint>
                            <MediaDuration>PT1S23N25F</MediaDuration>
                        </MediaTime>
                        <TemporalDecomposition>
                            <VideoSegment id="shot36031_10_RKF">
                                <MediaTime>
                                    <MediaTimePoint>T00:01:18:3F25</MediaTimePoint>
                                </MediaTime>
                            </VideoSegment>
                        </TemporalDecomposition>
                    </VideoSegment>
                    <VideoSegment id="shot36031_11">
                        <MediaTime>
                            <MediaTimePoint>T00:01:19:0F25</MediaTimePoint>
                            <MediaDuration>PT20N25F</MediaDuration>
                        </MediaTime>
                        <TemporalDecomposition>
                            <VideoSegment id="shot36031_11_RKF">
                                <MediaTime>
                                    <MediaTimePoint>T00:01:19:9F25</MediaTimePoint>
                                </MediaTime>
                            </VideoSegment>
                        </TemporalDecomposition>
                    </VideoSegment>
                    <VideoSegment id="shot36031_12">
                        <MediaTime>
                            <MediaTimePoint>T00:01:19:20F25</MediaTimePoint>
                            <MediaDuration>PT24N25F</MediaDuration>
                        </MediaTime>
                        <TemporalDecomposition>
                            <VideoSegment id="shot36031_12_RKF">
                                <MediaTime>
                                    <MediaTimePoint>T00:01:20:8F25</MediaTimePoint>
                                </MediaTime>
                            </VideoSegment>
                        </TemporalDecomposition>
                    </VideoSegment>
                    <VideoSegment id="shot36031_13">
                        <MediaTime>
                            <MediaTimePoint>T00:01:20:19F25</MediaTimePoint>
                            <MediaDuration>PT1S3N25F</MediaDuration>
                        </MediaTime>
                        <TemporalDecomposition>
                            <VideoSegment id="shot36031_13_RKF">
                                <MediaTime>
                                    <MediaTimePoint>T00:01:21:8F25</MediaTimePoint>
                                </MediaTime>
                            </VideoSegment>
                        </TemporalDecomposition>
                    </VideoSegment>
                    <VideoSegment id="shot36031_14">
                        <MediaTime>
                            <MediaTimePoint>T00:01:21:22F25</MediaTimePoint>
                            <MediaDuration>PT3S23N25F</MediaDuration>
                        </MediaTime>
                        <TemporalDecomposition>
                            <VideoSegment id="shot36031_14_RKF">
                                <MediaTime>
                                    <MediaTimePoint>T00:01:23:19F25</MediaTimePoint>
                                </MediaTime>
                            </VideoSegment>
                        </TemporalDecomposition>
                    </VideoSegment>
                    <VideoSegment id="shot36031_15">
                        <MediaTime>
                            <MediaTimePoint>T00:01:25:20F25</MediaTimePoint>
                            <MediaDuration>PT45S11N25F</MediaDuration>
                        </MediaTime>
                        <TemporalDecomposition>
                            <VideoSegment id="shot36031_15_RKF">
                                <MediaTime>
                                    <MediaTimePoint>T00:01:52:0F25</MediaTimePoint>
                                </MediaTime>
                            </VideoSegment>
                        </TemporalDecomposition>
                    </VideoSegment>
                    <VideoSegment id="shot36031_16">
                        <MediaTime>
                            <MediaTimePoint>T00:02:11:6F25</MediaTimePoint>
                            <MediaDuration>PT43S15N25F</MediaDuration>
                        </MediaTime>
                        <TemporalDecomposition>
                            <VideoSegment id="shot36031_16_RKF">
                                <MediaTime>
                                    <MediaTimePoint>T00:02:32:5F25</MediaTimePoint>
                                </MediaTime>
                            </VideoSegment>
                        </TemporalDecomposition>
                    </VideoSegment>
                    <VideoSegment id="shot36031_17">
                        <MediaTime>
                            <MediaTimePoint>T00:02:54:21F25</MediaTimePoint>
                            <MediaDuration>PT1S3N25F</MediaDuration>
                        </MediaTime>
                        <TemporalDecomposition>
                            <VideoSegment id="shot36031_17_RKF">
                                <MediaTime>
                                    <MediaTimePoint>T00:02:55:13F25</MediaTimePoint>
                                </MediaTime>
                            </VideoSegment>
                        </TemporalDecomposition>
                    </VideoSegment>
                    <VideoSegment id="shot36031_18">
                        <MediaTime>
                            <MediaTimePoint>T00:02:55:24F25</MediaTimePoint>
                            <MediaDuration>PT1S19N25F</MediaDuration>
                        </MediaTime>
                        <TemporalDecomposition>
                            <VideoSegment id="shot36031_18_RKF">
                                <MediaTime>
                                    <MediaTimePoint>T00:02:56:21F25</MediaTimePoint>
                                </MediaTime>
                            </VideoSegment>
                        </TemporalDecomposition>
                    </VideoSegment>
                    <VideoSegment id="shot36031_19">
                        <MediaTime>
                            <MediaTimePoint>T00:02:57:18F25</MediaTimePoint>
                            <MediaDuration>PT1S23N25F</MediaDuration>
                        </MediaTime>
                        <TemporalDecomposition>
                            <VideoSegment id="shot36031_19_RKF">
                                <MediaTime>
                                    <MediaTimePoint>T00:02:58:14F25</MediaTimePoint>
                                </MediaTime>
                            </VideoSegment>
                        </TemporalDecomposition>
                    </VideoSegment>
                    <VideoSegment id="shot36031_20">
                        <MediaTime>
                            <MediaTimePoint>T00:02:59:16F25</MediaTimePoint>
                            <MediaDuration>PT5S19N25F</MediaDuration>
                        </MediaTime>
                        <TemporalDecomposition>
                            <VideoSegment id="shot36031_20_RKF">
                                <MediaTime>
                                    <MediaTimePoint>T00:03:02:15F25</MediaTimePoint>
                                </MediaTime>
                            </VideoSegment>
                        </TemporalDecomposition>
                    </VideoSegment>
                    <VideoSegment id="shot36031_21">
                        <MediaTime>
                            <MediaTimePoint>T00:03:05:10F25</MediaTimePoint>
                            <MediaDuration>PT2S22N25F</MediaDuration>
                        </MediaTime>
                        <TemporalDecomposition>
                            <VideoSegment id="shot36031_21_RKF">
                                <MediaTime>
                                    <MediaTimePoint>T00:03:06:21F25</MediaTimePoint>
                                </MediaTime>
                            </VideoSegment>
                        </TemporalDecomposition>
                    </VideoSegment>
                    <VideoSegment id="shot36031_22">
                        <MediaTime>
                            <MediaTimePoint>T00:03:08:7F25</MediaTimePoint>
                            <MediaDuration>PT21S7N25F</MediaDuration>
                        </MediaTime>
                        <TemporalDecomposition>
                            <VideoSegment id="shot36031_22_RKF">
                                <MediaTime>
                                    <MediaTimePoint>T00:03:17:12F25</MediaTimePoint>
                                </MediaTime>
                            </VideoSegment>
                        </TemporalDecomposition>
                    </VideoSegment>
                    <VideoSegment id="shot36031_23">
                        <MediaTime>
                            <MediaTimePoint>T00:03:29:14F25</MediaTimePoint>
                            <MediaDuration>PT24S2N25F</MediaDuration>
                        </MediaTime>
                        <TemporalDecomposition>
                            <VideoSegment id="shot36031_23_RKF">
                                <MediaTime>
                                    <MediaTimePoint>T00:03:40:18F25</MediaTimePoint>
                                </MediaTime>
                            </VideoSegment>
                        </TemporalDecomposition>
                    </VideoSegment>
                    <VideoSegment id="shot36031_24">
                        <MediaTime>
                            <MediaTimePoint>T00:03:53:16F25</MediaTimePoint>
                            <MediaDuration>PT27S1N25F</MediaDuration>
                        </MediaTime>
                        <TemporalDecomposition>
                            <VideoSegment id="shot36031_24_RKF">
                                <MediaTime>
                                    <MediaTimePoint>T00:04:06:24F25</MediaTimePoint>
                                </MediaTime>
                            </VideoSegment>
                        </TemporalDecomposition>
                    </VideoSegment>
                    <VideoSegment id="shot36031_25">
                        <MediaTime>
                            <MediaTimePoint>T00:04:20:17F25</MediaTimePoint>
                            <MediaDuration>PT24N25F</MediaDuration>
                        </MediaTime>
                        <TemporalDecomposition>
                            <VideoSegment id="shot36031_25_RKF">
                                <MediaTime>
                                    <MediaTimePoint>T00:04:21:4F25</MediaTimePoint>
                                </MediaTime>
                            </VideoSegment>
                        </TemporalDecomposition>
                    </VideoSegment>
                    <VideoSegment id="shot36031_26">
                        <MediaTime>
                            <MediaTimePoint>T00:04:21:16F25</MediaTimePoint>
                            <MediaDuration>PT24N25F</MediaDuration>
                        </MediaTime>
                        <TemporalDecomposition>
                            <VideoSegment id="shot36031_26_RKF">
                                <MediaTime>
                                    <MediaTimePoint>T00:04:22:5F25</MediaTimePoint>
                                </MediaTime>
                            </VideoSegment>
                        </TemporalDecomposition>
                    </VideoSegment>
                    <VideoSegment id="shot36031_27">
                        <MediaTime>
                            <MediaTimePoint>T00:04:22:15F25</MediaTimePoint>
                            <MediaDuration>PT3S17N25F</MediaDuration>
                        </MediaTime>
                        <TemporalDecomposition>
                            <VideoSegment id="shot36031_27_RKF">
                                <MediaTime>
                                    <MediaTimePoint>T00:04:24:3F25</MediaTimePoint>
                                </MediaTime>
                            </VideoSegment>
                        </TemporalDecomposition>
                    </VideoSegment>
                    <VideoSegment id="shot36031_28">
                        <MediaTime>
                            <MediaTimePoint>T00:04:26:7F25</MediaTimePoint>
                            <MediaDuration>PT4S20N25F</MediaDuration>
                        </MediaTime>
                        <TemporalDecomposition>
                            <VideoSegment id="shot36031_28_RKF">
                                <MediaTime>
                                    <MediaTimePoint>T00:04:28:11F25</MediaTimePoint>
                                </MediaTime>
                            </VideoSegment>
                        </TemporalDecomposition>
                    </VideoSegment>
                    <VideoSegment id="shot36031_29">
                        <MediaTime>
                            <MediaTimePoint>T00:04:31:2F25</MediaTimePoint>
                            <MediaDuration>PT4N25F</MediaDuration>
                        </MediaTime>
                        <TemporalDecomposition>
                            <VideoSegment id="shot36031_29_RKF">
                                <MediaTime>
                                    <MediaTimePoint>T00:04:31:4F25</MediaTimePoint>
                                </MediaTime>
                            </VideoSegment>
                        </TemporalDecomposition>
                    </VideoSegment>
                    <VideoSegment id="shot36031_30">
                        <MediaTime>
                            <MediaTimePoint>T00:04:31:6F25</MediaTimePoint>
                            <MediaDuration>PT20N25F</MediaDuration>
                        </MediaTime>
                        <TemporalDecomposition>
                            <VideoSegment id="shot36031_30_RKF">
                                <MediaTime>
                                    <MediaTimePoint>T00:04:31:18F25</MediaTimePoint>
                                </MediaTime>
                            </VideoSegment>
                        </TemporalDecomposition>
                    </VideoSegment>
                    <VideoSegment id="shot36031_31">
                        <MediaTime>
                            <MediaTimePoint>T00:04:32:1F25</MediaTimePoint>
                            <MediaDuration>PT4N25F</MediaDuration>
                        </MediaTime>
                        <TemporalDecomposition>
                            <VideoSegment id="shot36031_31_RKF">
                                <MediaTime>
                                    <MediaTimePoint>T00:04:32:2F25</MediaTimePoint>
                                </MediaTime>
                            </VideoSegment>
                        </TemporalDecomposition>
                    </VideoSegment>
                    <VideoSegment id="shot36031_32">
                        <MediaTime>
                            <MediaTimePoint>T00:04:32:5F25</MediaTimePoint>
                            <MediaDuration>PT1S19N25F</MediaDuration>
                        </MediaTime>
                        <TemporalDecomposition>
                            <VideoSegment id="shot36031_32_RKF">
                                <MediaTime>
                                    <MediaTimePoint>T00:04:32:22F25</MediaTimePoint>
                                </MediaTime>
                            </VideoSegment>
                        </TemporalDecomposition>
                    </VideoSegment>
                    <VideoSegment id="shot36031_33">
                        <MediaTime>
                            <MediaTimePoint>T00:04:33:24F25</MediaTimePoint>
                            <MediaDuration>PT4N25F</MediaDuration>
                        </MediaTime>
                        <TemporalDecomposition>
                            <VideoSegment id="shot36031_33_RKF">
                                <MediaTime>
                                    <MediaTimePoint>T00:04:34:1F25</MediaTimePoint>
                                </MediaTime>
                            </VideoSegment>
                        </TemporalDecomposition>
                    </VideoSegment>
                    <VideoSegment id="shot36031_34">
                        <MediaTime>
                            <MediaTimePoint>T00:04:34:3F25</MediaTimePoint>
                            <MediaDuration>PT24N25F</MediaDuration>
                        </MediaTime>
                        <TemporalDecomposition>
                            <VideoSegment id="shot36031_34_RKF">
                                <MediaTime>
                                    <MediaTimePoint>T00:04:34:15F25</MediaTimePoint>
                                </MediaTime>
                            </VideoSegment>
                        </TemporalDecomposition>
                    </VideoSegment>
                    <VideoSegment id="shot36031_35">
                        <MediaTime>
                            <MediaTimePoint>T00:04:35:2F25</MediaTimePoint>
                            <MediaDuration>PT24N25F</MediaDuration>
                        </MediaTime>
                        <TemporalDecomposition>
                            <VideoSegment id="shot36031_35_RKF">
                                <MediaTime>
                                    <MediaTimePoint>T00:04:35:14F25</MediaTimePoint>
                                </MediaTime>
                            </VideoSegment>
                        </TemporalDecomposition>
                    </VideoSegment>
                    <VideoSegment id="shot36031_36">
                        <MediaTime>
                            <MediaTimePoint>T00:04:36:1F25</MediaTimePoint>
                            <MediaDuration>PT20N25F</MediaDuration>
                        </MediaTime>
                        <TemporalDecomposition>
                            <VideoSegment id="shot36031_36_RKF">
                                <MediaTime>
                                    <MediaTimePoint>T00:04:36:9F25</MediaTimePoint>
                                </MediaTime>
                            </VideoSegment>
                        </TemporalDecomposition>
                    </VideoSegment>
                    <VideoSegment id="shot36031_37">
                        <MediaTime>
                            <MediaTimePoint>T00:04:36:21F25</MediaTimePoint>
                            <MediaDuration>PT4N25F</MediaDuration>
                        </MediaTime>
                        <TemporalDecomposition>
                            <VideoSegment id="shot36031_37_RKF">
                                <MediaTime>
                                    <MediaTimePoint>T00:04:36:22F25</MediaTimePoint>
                                </MediaTime>
                            </VideoSegment>
                        </TemporalDecomposition>
                    </VideoSegment>
                    <VideoSegment id="shot36031_38">
                        <MediaTime>
                            <MediaTimePoint>T00:04:37:0F25</MediaTimePoint>
                            <MediaDuration>PT20N25F</MediaDuration>
                        </MediaTime>
                        <TemporalDecomposition>
                            <VideoSegment id="shot36031_38_RKF">
                                <MediaTime>
                                    <MediaTimePoint>T00:04:37:9F25</MediaTimePoint>
                                </MediaTime>
                            </VideoSegment>
                        </TemporalDecomposition>
                    </VideoSegment>
                    <VideoSegment id="shot36031_39">
                        <MediaTime>
                            <MediaTimePoint>T00:04:37:20F25</MediaTimePoint>
                            <MediaDuration>PT18N25F</MediaDuration>
                        </MediaTime>
                        <TemporalDecomposition>
                            <VideoSegment id="shot36031_39_RKF">
                                <MediaTime>
                                    <MediaTimePoint>T00:04:38:4F25</MediaTimePoint>
                                </MediaTime>
                            </VideoSegment>
                        </TemporalDecomposition>
                    </VideoSegment>
                    <VideoSegment id="shot36031_40">
                        <MediaTime>
                            <MediaTimePoint>T00:04:38:13F25</MediaTimePoint>
                            <MediaDuration>PT6N25F</MediaDuration>
                        </MediaTime>
                        <TemporalDecomposition>
                            <VideoSegment id="shot36031_40_RKF">
                                <MediaTime>
                                    <MediaTimePoint>T00:04:38:16F25</MediaTimePoint>
                                </MediaTime>
                            </VideoSegment>
                        </TemporalDecomposition>
                    </VideoSegment>
                    <VideoSegment id="shot36031_41">
                        <MediaTime>
                            <MediaTimePoint>T00:04:38:19F25</MediaTimePoint>
                            <MediaDuration>PT4N25F</MediaDuration>
                        </MediaTime>
                        <TemporalDecomposition>
                            <VideoSegment id="shot36031_41_RKF">
                                <MediaTime>
                                    <MediaTimePoint>T00:04:38:21F25</MediaTimePoint>
                                </MediaTime>
                            </VideoSegment>
                        </TemporalDecomposition>
                    </VideoSegment>
                    <VideoSegment id="shot36031_42">
                        <MediaTime>
                            <MediaTimePoint>T00:04:38:23F25</MediaTimePoint>
                            <MediaDuration>PT6S18N25F</MediaDuration>
                        </MediaTime>
                        <TemporalDecomposition>
                            <VideoSegment id="shot36031_42_RKF">
                                <MediaTime>
                                    <MediaTimePoint>T00:04:42:12F25</MediaTimePoint>
                                </MediaTime>
                            </VideoSegment>
                        </TemporalDecomposition>
                    </VideoSegment>
                    <VideoSegment id="shot36031_43">
                        <MediaTime>
                            <MediaTimePoint>T00:04:45:16F25</MediaTimePoint>
                            <MediaDuration>PT20N25F</MediaDuration>
                        </MediaTime>
                        <TemporalDecomposition>
                            <VideoSegment id="shot36031_43_RKF">
                                <MediaTime>
                                    <MediaTimePoint>T00:04:46:0F25</MediaTimePoint>
                                </MediaTime>
                            </VideoSegment>
                        </TemporalDecomposition>
                    </VideoSegment>
                    <VideoSegment id="shot36031_44">
                        <MediaTime>
                            <MediaTimePoint>T00:04:46:11F25</MediaTimePoint>
                            <MediaDuration>PT1S3N25F</MediaDuration>
                        </MediaTime>
                        <TemporalDecomposition>
                            <VideoSegment id="shot36031_44_RKF">
                                <MediaTime>
                                    <MediaTimePoint>T00:04:46:23F25</MediaTimePoint>
                                </MediaTime>
                            </VideoSegment>
                        </TemporalDecomposition>
                    </VideoSegment>
                    <VideoSegment id="shot36031_45">
                        <MediaTime>
                            <MediaTimePoint>T00:04:47:14F25</MediaTimePoint>
                            <MediaDuration>PT20N25F</MediaDuration>
                        </MediaTime>
                        <TemporalDecomposition>
                            <VideoSegment id="shot36031_45_RKF">
                                <MediaTime>
                                    <MediaTimePoint>T00:04:48:0F25</MediaTimePoint>
                                </MediaTime>
                            </VideoSegment>
                        </TemporalDecomposition>
                    </VideoSegment>
                    <VideoSegment id="shot36031_46">
                        <MediaTime>
                            <MediaTimePoint>T00:04:48:9F25</MediaTimePoint>
                            <MediaDuration>PT4N25F</MediaDuration>
                        </MediaTime>
                        <TemporalDecomposition>
                            <VideoSegment id="shot36031_46_RKF">
                                <MediaTime>
                                    <MediaTimePoint>T00:04:48:11F25</MediaTimePoint>
                                </MediaTime>
                            </VideoSegment>
                        </TemporalDecomposition>
                    </VideoSegment>
                    <VideoSegment id="shot36031_47">
                        <MediaTime>
                            <MediaTimePoint>T00:04:48:13F25</MediaTimePoint>
                            <MediaDuration>PT24N25F</MediaDuration>
                        </MediaTime>
                        <TemporalDecomposition>
                            <VideoSegment id="shot36031_47_RKF">
                                <MediaTime>
                                    <MediaTimePoint>T00:04:48:24F25</MediaTimePoint>
                                </MediaTime>
                            </VideoSegment>
                        </TemporalDecomposition>
                    </VideoSegment>
                    <VideoSegment id="shot36031_48">
                        <MediaTime>
                            <MediaTimePoint>T00:04:49:12F25</MediaTimePoint>
                            <MediaDuration>PT6S18N25F</MediaDuration>
                        </MediaTime>
                        <TemporalDecomposition>
                            <VideoSegment id="shot36031_48_RKF">
                                <MediaTime>
                                    <MediaTimePoint>T00:04:52:22F25</MediaTimePoint>
                                </MediaTime>
                            </VideoSegment>
                        </TemporalDecomposition>
                    </VideoSegment>
                    <VideoSegment id="shot36031_49">
                        <MediaTime>
                            <MediaTimePoint>T00:04:56:5F25</MediaTimePoint>
                            <MediaDuration>PT1S11N25F</MediaDuration>
                        </MediaTime>
                        <TemporalDecomposition>
                            <VideoSegment id="shot36031_49_RKF">
                                <MediaTime>
                                    <MediaTimePoint>T00:04:56:22F25</MediaTimePoint>
                                </MediaTime>
                            </VideoSegment>
                        </TemporalDecomposition>
                    </VideoSegment>
                    <VideoSegment id="shot36031_50">
                        <MediaTime>
                            <MediaTimePoint>T00:04:57:16F25</MediaTimePoint>
                            <MediaDuration>PT15S14N25F</MediaDuration>
                        </MediaTime>
                        <TemporalDecomposition>
                            <VideoSegment id="shot36031_50_RKF">
                                <MediaTime>
                                    <MediaTimePoint>T00:05:04:16F25</MediaTimePoint>
                                </MediaTime>
                            </VideoSegment>
                        </TemporalDecomposition>
                    </VideoSegment>
                    <VideoSegment id="shot36031_51">
                        <MediaTime>
                            <MediaTimePoint>T00:05:13:5F25</MediaTimePoint>
                            <MediaDuration>PT11S13N25F</MediaDuration>
                        </MediaTime>
                        <TemporalDecomposition>
                            <VideoSegment id="shot36031_51_RKF">
                                <MediaTime>
                                    <MediaTimePoint>T00:05:19:18F25</MediaTimePoint>
                                </MediaTime>
                            </VideoSegment>
                        </TemporalDecomposition>
                    </VideoSegment>
                    <VideoSegment id="shot36031_52">
                        <MediaTime>
                            <MediaTimePoint>T00:05:24:18F25</MediaTimePoint>
                            <MediaDuration>PT10S23N25F</MediaDuration>
                        </MediaTime>
                        <TemporalDecomposition>
                            <VideoSegment id="shot36031_52_RKF">
                                <MediaTime>
                                    <MediaTimePoint>T00:05:30:19F25</MediaTimePoint>
                                </MediaTime>
                            </VideoSegment>
                        </TemporalDecomposition>
                    </VideoSegment>
                    <VideoSegment id="shot36031_53">
                        <MediaTime>
                            <MediaTimePoint>T00:05:35:16F25</MediaTimePoint>
                            <MediaDuration>PT4N25F</MediaDuration>
                        </MediaTime>
                        <TemporalDecomposition>
                            <VideoSegment id="shot36031_53_RKF">
                                <MediaTime>
                                    <MediaTimePoint>T00:05:35:18F25</MediaTimePoint>
                                </MediaTime>
                            </VideoSegment>
                        </TemporalDecomposition>
                    </VideoSegment>
                    <VideoSegment id="shot36031_54">
                        <MediaTime>
                            <MediaTimePoint>T00:05:35:20F25</MediaTimePoint>
                            <MediaDuration>PT1S23N25F</MediaDuration>
                        </MediaTime>
                        <TemporalDecomposition>
                            <VideoSegment id="shot36031_54_RKF">
                                <MediaTime>
                                    <MediaTimePoint>T00:05:36:21F25</MediaTimePoint>
                                </MediaTime>
                            </VideoSegment>
                        </TemporalDecomposition>
                    </VideoSegment>
                    <VideoSegment id="shot36031_55">
                        <MediaTime>
                            <MediaTimePoint>T00:05:37:18F25</MediaTimePoint>
                            <MediaDuration>PT1S1N25F</MediaDuration>
                        </MediaTime>
                        <TemporalDecomposition>
                            <VideoSegment id="shot36031_55_RKF">
                                <MediaTime>
                                    <MediaTimePoint>T00:05:38:6F25</MediaTimePoint>
                                </MediaTime>
                            </VideoSegment>
                        </TemporalDecomposition>
                    </VideoSegment>
                    <VideoSegment id="shot36031_56">
                        <MediaTime>
                            <MediaTimePoint>T00:05:38:19F25</MediaTimePoint>
                            <MediaDuration>PT7S21N25F</MediaDuration>
                        </MediaTime>
                        <TemporalDecomposition>
                            <VideoSegment id="shot36031_56_RKF">
                                <MediaTime>
                                    <MediaTimePoint>T00:05:42:22F25</MediaTimePoint>
                                </MediaTime>
                            </VideoSegment>
                        </TemporalDecomposition>
                    </VideoSegment>
                    <VideoSegment id="shot36031_57">
                        <MediaTime>
                            <MediaTimePoint>T00:05:46:15F25</MediaTimePoint>
                            <MediaDuration>PT24N25F</MediaDuration>
                        </MediaTime>
                        <TemporalDecomposition>
                            <VideoSegment id="shot36031_57_RKF">
                                <MediaTime>
                                    <MediaTimePoint>T00:05:47:2F25</MediaTimePoint>
                                </MediaTime>
                            </VideoSegment>
                        </TemporalDecomposition>
                    </VideoSegment>
                    <VideoSegment id="shot36031_58">
                        <MediaTime>
                            <MediaTimePoint>T00:05:47:14F25</MediaTimePoint>
                            <MediaDuration>PT24N25F</MediaDuration>
                        </MediaTime>
                        <TemporalDecomposition>
                            <VideoSegment id="shot36031_58_RKF">
                                <MediaTime>
                                    <MediaTimePoint>T00:05:48:0F25</MediaTimePoint>
                                </MediaTime>
                            </VideoSegment>
                        </TemporalDecomposition>
                    </VideoSegment>
                    <VideoSegment id="shot36031_59">
                        <MediaTime>
                            <MediaTimePoint>T00:05:48:13F25</MediaTimePoint>
                            <MediaDuration>PT50S5N25F</MediaDuration>
                        </MediaTime>
                        <TemporalDecomposition>
                            <VideoSegment id="shot36031_59_RKF">
                                <MediaTime>
                                    <MediaTimePoint>T00:06:09:24F25</MediaTimePoint>
                                </MediaTime>
                            </VideoSegment>
                        </TemporalDecomposition>
                    </VideoSegment>
                    <VideoSegment id="shot36031_60">
                        <MediaTime>
                            <MediaTimePoint>T00:06:38:18F25</MediaTimePoint>
                            <MediaDuration>PT6S3N25F</MediaDuration>
                        </MediaTime>
                        <TemporalDecomposition>
                            <VideoSegment id="shot36031_60_RKF">
                                <MediaTime>
                                    <MediaTimePoint>T00:06:41:11F25</MediaTimePoint>
                                </MediaTime>
                            </VideoSegment>
                        </TemporalDecomposition>
                    </VideoSegment>
                    <VideoSegment id="shot36031_61">
                        <MediaTime>
                            <MediaTimePoint>T00:06:44:21F25</MediaTimePoint>
                            <MediaDuration>PT2S1N25F</MediaDuration>
                        </MediaTime>
                        <TemporalDecomposition>
                            <VideoSegment id="shot36031_61_RKF">
                                <MediaTime>
                                    <MediaTimePoint>T00:06:46:6F25</MediaTimePoint>
                                </MediaTime>
                            </VideoSegment>
                        </TemporalDecomposition>
                    </VideoSegment>
                </TemporalDecomposition>
            </Video>
        </MultimediaContent>
    </Description>
</Mpeg7>
