<?xml version="1.0" encoding="UTF-8"?>
<Mpeg7 xmlns="urn:mpeg:mpeg7:schema:2001" xmlns:xsi="http://www.w3.org/2001/XMLSchema-instance" xmlns:mpeg7="urn:mpeg:mpeg7:schema:2001" xsi:schemaLocation="urn:mpeg:mpeg7:schema:2001 Mpeg7-2001.xsd">
    <Description xsi:type="ContentEntityType">
        <MultimediaContent xsi:type="VideoType">
            <Video id="TRECVID2016_38981">
                <MediaLocator><MediaUri>CreatingWidgetsWithDashcode-MactipsVideos._-o-_.03-Creating-Widgets-With-Dashcode_512kb.mp4</MediaUri></MediaLocator>
                <MediaTime>
                    <MediaTimePoint>T00:00:00:0F30</MediaTimePoint>
                    <MediaDuration>PT8M46S22N30F</MediaDuration>
                </MediaTime>
                <TemporalDecomposition gap="false" overlap="false">
                    <VideoSegment id="shot38981_1">
                        <MediaTime>
                            <MediaTimePoint>T00:00:00:0F30</MediaTimePoint>
                            <MediaDuration>PT33S8N30F</MediaDuration>
                        </MediaTime>
                        <TemporalDecomposition>
                            <VideoSegment id="shot38981_1_RKF">
                                <MediaTime>
                                    <MediaTimePoint>T00:00:16:14F30</MediaTimePoint>
                                </MediaTime>
                            </VideoSegment>
                        </TemporalDecomposition>
                    </VideoSegment>
                    <VideoSegment id="shot38981_2">
                        <MediaTime>
                            <MediaTimePoint>T00:00:33:8F30</MediaTimePoint>
                            <MediaDuration>PT37S14N30F</MediaDuration>
                        </MediaTime>
                        <TemporalDecomposition>
                            <VideoSegment id="shot38981_2_RKF">
                                <MediaTime>
                                    <MediaTimePoint>T00:00:54:13F30</MediaTimePoint>
                                </MediaTime>
                            </VideoSegment>
                        </TemporalDecomposition>
                    </VideoSegment>
                    <VideoSegment id="shot38981_3">
                        <MediaTime>
                            <MediaTimePoint>T00:01:10:22F30</MediaTimePoint>
                            <MediaDuration>PT7S3N30F</MediaDuration>
                        </MediaTime>
                        <TemporalDecomposition>
                            <VideoSegment id="shot38981_3_RKF">
                                <MediaTime>
                                    <MediaTimePoint>T00:01:14:10F30</MediaTimePoint>
                                </MediaTime>
                            </VideoSegment>
                        </TemporalDecomposition>
                    </VideoSegment>
                    <VideoSegment id="shot38981_4">
                        <MediaTime>
                            <MediaTimePoint>T00:01:17:25F30</MediaTimePoint>
                            <MediaDuration>PT2N30F</MediaDuration>
                        </MediaTime>
                        <TemporalDecomposition>
                            <VideoSegment id="shot38981_4_RKF">
                                <MediaTime>
                                    <MediaTimePoint>T00:01:17:26F30</MediaTimePoint>
                                </MediaTime>
                            </VideoSegment>
                        </TemporalDecomposition>
                    </VideoSegment>
                    <VideoSegment id="shot38981_5">
                        <MediaTime>
                            <MediaTimePoint>T00:01:17:27F30</MediaTimePoint>
                            <MediaDuration>PT9S20N30F</MediaDuration>
                        </MediaTime>
                        <TemporalDecomposition>
                            <VideoSegment id="shot38981_5_RKF">
                                <MediaTime>
                                    <MediaTimePoint>T00:01:22:20F30</MediaTimePoint>
                                </MediaTime>
                            </VideoSegment>
                        </TemporalDecomposition>
                    </VideoSegment>
                    <VideoSegment id="shot38981_6">
                        <MediaTime>
                            <MediaTimePoint>T00:01:27:17F30</MediaTimePoint>
                            <MediaDuration>PT3N30F</MediaDuration>
                        </MediaTime>
                        <TemporalDecomposition>
                            <VideoSegment id="shot38981_6_RKF">
                                <MediaTime>
                                    <MediaTimePoint>T00:01:27:19F30</MediaTimePoint>
                                </MediaTime>
                            </VideoSegment>
                        </TemporalDecomposition>
                    </VideoSegment>
                    <VideoSegment id="shot38981_7">
                        <MediaTime>
                            <MediaTimePoint>T00:01:27:20F30</MediaTimePoint>
                            <MediaDuration>PT58S9N30F</MediaDuration>
                        </MediaTime>
                        <TemporalDecomposition>
                            <VideoSegment id="shot38981_7_RKF">
                                <MediaTime>
                                    <MediaTimePoint>T00:01:28:9F30</MediaTimePoint>
                                </MediaTime>
                            </VideoSegment>
                        </TemporalDecomposition>
                    </VideoSegment>
                    <VideoSegment id="shot38981_8">
                        <MediaTime>
                            <MediaTimePoint>T00:02:25:29F30</MediaTimePoint>
                            <MediaDuration>PT1S6N30F</MediaDuration>
                        </MediaTime>
                        <TemporalDecomposition>
                            <VideoSegment id="shot38981_8_RKF">
                                <MediaTime>
                                    <MediaTimePoint>T00:02:26:16F30</MediaTimePoint>
                                </MediaTime>
                            </VideoSegment>
                        </TemporalDecomposition>
                    </VideoSegment>
                    <VideoSegment id="shot38981_9">
                        <MediaTime>
                            <MediaTimePoint>T00:02:27:5F30</MediaTimePoint>
                            <MediaDuration>PT8S19N30F</MediaDuration>
                        </MediaTime>
                        <TemporalDecomposition>
                            <VideoSegment id="shot38981_9_RKF">
                                <MediaTime>
                                    <MediaTimePoint>T00:02:31:21F30</MediaTimePoint>
                                </MediaTime>
                            </VideoSegment>
                        </TemporalDecomposition>
                    </VideoSegment>
                    <VideoSegment id="shot38981_10">
                        <MediaTime>
                            <MediaTimePoint>T00:02:35:24F30</MediaTimePoint>
                            <MediaDuration>PT21S14N30F</MediaDuration>
                        </MediaTime>
                        <TemporalDecomposition>
                            <VideoSegment id="shot38981_10_RKF">
                                <MediaTime>
                                    <MediaTimePoint>T00:02:46:14F30</MediaTimePoint>
                                </MediaTime>
                            </VideoSegment>
                        </TemporalDecomposition>
                    </VideoSegment>
                    <VideoSegment id="shot38981_11">
                        <MediaTime>
                            <MediaTimePoint>T00:02:57:8F30</MediaTimePoint>
                            <MediaDuration>PT5S4N30F</MediaDuration>
                        </MediaTime>
                        <TemporalDecomposition>
                            <VideoSegment id="shot38981_11_RKF">
                                <MediaTime>
                                    <MediaTimePoint>T00:02:59:26F30</MediaTimePoint>
                                </MediaTime>
                            </VideoSegment>
                        </TemporalDecomposition>
                    </VideoSegment>
                    <VideoSegment id="shot38981_12">
                        <MediaTime>
                            <MediaTimePoint>T00:03:02:12F30</MediaTimePoint>
                            <MediaDuration>PT5S29N30F</MediaDuration>
                        </MediaTime>
                        <TemporalDecomposition>
                            <VideoSegment id="shot38981_12_RKF">
                                <MediaTime>
                                    <MediaTimePoint>T00:03:05:10F30</MediaTimePoint>
                                </MediaTime>
                            </VideoSegment>
                        </TemporalDecomposition>
                    </VideoSegment>
                    <VideoSegment id="shot38981_13">
                        <MediaTime>
                            <MediaTimePoint>T00:03:08:11F30</MediaTimePoint>
                            <MediaDuration>PT5N30F</MediaDuration>
                        </MediaTime>
                        <TemporalDecomposition>
                            <VideoSegment id="shot38981_13_RKF">
                                <MediaTime>
                                    <MediaTimePoint>T00:03:08:13F30</MediaTimePoint>
                                </MediaTime>
                            </VideoSegment>
                        </TemporalDecomposition>
                    </VideoSegment>
                    <VideoSegment id="shot38981_14">
                        <MediaTime>
                            <MediaTimePoint>T00:03:08:16F30</MediaTimePoint>
                            <MediaDuration>PT7N30F</MediaDuration>
                        </MediaTime>
                        <TemporalDecomposition>
                            <VideoSegment id="shot38981_14_RKF">
                                <MediaTime>
                                    <MediaTimePoint>T00:03:08:19F30</MediaTimePoint>
                                </MediaTime>
                            </VideoSegment>
                        </TemporalDecomposition>
                    </VideoSegment>
                    <VideoSegment id="shot38981_15">
                        <MediaTime>
                            <MediaTimePoint>T00:03:08:23F30</MediaTimePoint>
                            <MediaDuration>PT16N30F</MediaDuration>
                        </MediaTime>
                        <TemporalDecomposition>
                            <VideoSegment id="shot38981_15_RKF">
                                <MediaTime>
                                    <MediaTimePoint>T00:03:09:1F30</MediaTimePoint>
                                </MediaTime>
                            </VideoSegment>
                        </TemporalDecomposition>
                    </VideoSegment>
                    <VideoSegment id="shot38981_16">
                        <MediaTime>
                            <MediaTimePoint>T00:03:09:9F30</MediaTimePoint>
                            <MediaDuration>PT25N30F</MediaDuration>
                        </MediaTime>
                        <TemporalDecomposition>
                            <VideoSegment id="shot38981_16_RKF">
                                <MediaTime>
                                    <MediaTimePoint>T00:03:09:21F30</MediaTimePoint>
                                </MediaTime>
                            </VideoSegment>
                        </TemporalDecomposition>
                    </VideoSegment>
                    <VideoSegment id="shot38981_17">
                        <MediaTime>
                            <MediaTimePoint>T00:03:10:4F30</MediaTimePoint>
                            <MediaDuration>PT2M12S8N30F</MediaDuration>
                        </MediaTime>
                        <TemporalDecomposition>
                            <VideoSegment id="shot38981_17_RKF">
                                <MediaTime>
                                    <MediaTimePoint>T00:03:34:19F30</MediaTimePoint>
                                </MediaTime>
                            </VideoSegment>
                        </TemporalDecomposition>
                    </VideoSegment>
                    <VideoSegment id="shot38981_18">
                        <MediaTime>
                            <MediaTimePoint>T00:05:22:12F30</MediaTimePoint>
                            <MediaDuration>PT12N30F</MediaDuration>
                        </MediaTime>
                        <TemporalDecomposition>
                            <VideoSegment id="shot38981_18_RKF">
                                <MediaTime>
                                    <MediaTimePoint>T00:05:22:17F30</MediaTimePoint>
                                </MediaTime>
                            </VideoSegment>
                        </TemporalDecomposition>
                    </VideoSegment>
                    <VideoSegment id="shot38981_19">
                        <MediaTime>
                            <MediaTimePoint>T00:05:22:24F30</MediaTimePoint>
                            <MediaDuration>PT15S18N30F</MediaDuration>
                        </MediaTime>
                        <TemporalDecomposition>
                            <VideoSegment id="shot38981_19_RKF">
                                <MediaTime>
                                    <MediaTimePoint>T00:05:30:10F30</MediaTimePoint>
                                </MediaTime>
                            </VideoSegment>
                        </TemporalDecomposition>
                    </VideoSegment>
                    <VideoSegment id="shot38981_20">
                        <MediaTime>
                            <MediaTimePoint>T00:05:38:12F30</MediaTimePoint>
                            <MediaDuration>PT12N30F</MediaDuration>
                        </MediaTime>
                        <TemporalDecomposition>
                            <VideoSegment id="shot38981_20_RKF">
                                <MediaTime>
                                    <MediaTimePoint>T00:05:38:17F30</MediaTimePoint>
                                </MediaTime>
                            </VideoSegment>
                        </TemporalDecomposition>
                    </VideoSegment>
                    <VideoSegment id="shot38981_21">
                        <MediaTime>
                            <MediaTimePoint>T00:05:38:24F30</MediaTimePoint>
                            <MediaDuration>PT22S22N30F</MediaDuration>
                        </MediaTime>
                        <TemporalDecomposition>
                            <VideoSegment id="shot38981_21_RKF">
                                <MediaTime>
                                    <MediaTimePoint>T00:05:50:4F30</MediaTimePoint>
                                </MediaTime>
                            </VideoSegment>
                        </TemporalDecomposition>
                    </VideoSegment>
                    <VideoSegment id="shot38981_22">
                        <MediaTime>
                            <MediaTimePoint>T00:06:01:16F30</MediaTimePoint>
                            <MediaDuration>PT26N30F</MediaDuration>
                        </MediaTime>
                        <TemporalDecomposition>
                            <VideoSegment id="shot38981_22_RKF">
                                <MediaTime>
                                    <MediaTimePoint>T00:06:01:28F30</MediaTimePoint>
                                </MediaTime>
                            </VideoSegment>
                        </TemporalDecomposition>
                    </VideoSegment>
                    <VideoSegment id="shot38981_23">
                        <MediaTime>
                            <MediaTimePoint>T00:06:02:12F30</MediaTimePoint>
                            <MediaDuration>PT2M10S6N30F</MediaDuration>
                        </MediaTime>
                        <TemporalDecomposition>
                            <VideoSegment id="shot38981_23_RKF">
                                <MediaTime>
                                    <MediaTimePoint>T00:06:18:18F30</MediaTimePoint>
                                </MediaTime>
                            </VideoSegment>
                        </TemporalDecomposition>
                    </VideoSegment>
                    <VideoSegment id="shot38981_24">
                        <MediaTime>
                            <MediaTimePoint>T00:08:12:18F30</MediaTimePoint>
                            <MediaDuration>PT26S19N30F</MediaDuration>
                        </MediaTime>
                        <TemporalDecomposition>
                            <VideoSegment id="shot38981_24_RKF">
                                <MediaTime>
                                    <MediaTimePoint>T00:08:26:9F30</MediaTimePoint>
                                </MediaTime>
                            </VideoSegment>
                        </TemporalDecomposition>
                    </VideoSegment>
                    <VideoSegment id="shot38981_25">
                        <MediaTime>
                            <MediaTimePoint>T00:08:39:7F30</MediaTimePoint>
                            <MediaDuration>PT4N30F</MediaDuration>
                        </MediaTime>
                        <TemporalDecomposition>
                            <VideoSegment id="shot38981_25_RKF">
                                <MediaTime>
                                    <MediaTimePoint>T00:08:39:7F30</MediaTimePoint>
                                </MediaTime>
                            </VideoSegment>
                        </TemporalDecomposition>
                    </VideoSegment>
                    <VideoSegment id="shot38981_26">
                        <MediaTime>
                            <MediaTimePoint>T00:08:39:11F30</MediaTimePoint>
                            <MediaDuration>PT4N30F</MediaDuration>
                        </MediaTime>
                        <TemporalDecomposition>
                            <VideoSegment id="shot38981_26_RKF">
                                <MediaTime>
                                    <MediaTimePoint>T00:08:39:14F30</MediaTimePoint>
                                </MediaTime>
                            </VideoSegment>
                        </TemporalDecomposition>
                    </VideoSegment>
                    <VideoSegment id="shot38981_27">
                        <MediaTime>
                            <MediaTimePoint>T00:08:39:15F30</MediaTimePoint>
                            <MediaDuration>PT24N30F</MediaDuration>
                        </MediaTime>
                        <TemporalDecomposition>
                            <VideoSegment id="shot38981_27_RKF">
                                <MediaTime>
                                    <MediaTimePoint>T00:08:39:26F30</MediaTimePoint>
                                </MediaTime>
                            </VideoSegment>
                        </TemporalDecomposition>
                    </VideoSegment>
                    <VideoSegment id="shot38981_28">
                        <MediaTime>
                            <MediaTimePoint>T00:08:40:9F30</MediaTimePoint>
                            <MediaDuration>PT20N30F</MediaDuration>
                        </MediaTime>
                        <TemporalDecomposition>
                            <VideoSegment id="shot38981_28_RKF">
                                <MediaTime>
                                    <MediaTimePoint>T00:08:40:15F30</MediaTimePoint>
                                </MediaTime>
                            </VideoSegment>
                        </TemporalDecomposition>
                    </VideoSegment>
                    <VideoSegment id="shot38981_29">
                        <MediaTime>
                            <MediaTimePoint>T00:08:40:29F30</MediaTimePoint>
                            <MediaDuration>PT5S23N30F</MediaDuration>
                        </MediaTime>
                        <TemporalDecomposition>
                            <VideoSegment id="shot38981_29_RKF">
                                <MediaTime>
                                    <MediaTimePoint>T00:08:43:26F30</MediaTimePoint>
                                </MediaTime>
                            </VideoSegment>
                        </TemporalDecomposition>
                    </VideoSegment>
                </TemporalDecomposition>
            </Video>
        </MultimediaContent>
    </Description>
</Mpeg7>
